MANIFEST.in
README.md
pyproject.toml
setup.cfg
setup.py
bin/functional_hypergeom_test
src/mbf/__init__.py
src/mbf.egg-info/PKG-INFO
src/mbf.egg-info/SOURCES.txt
src/mbf.egg-info/dependency_links.txt
src/mbf.egg-info/entry_points.txt
src/mbf.egg-info/not-zip-safe
src/mbf.egg-info/requires.txt
src/mbf.egg-info/top_level.txt
src/mbf/align/__init__.py
src/mbf/align/_common.pyx
src/mbf/align/exceptions.py
src/mbf/align/fastq2.pyx
src/mbf/align/lanes.py
src/mbf/align/post_process.py
src/mbf/align/raw.py
src/mbf/align/strategies.py
src/mbf/align/tenx.py
src/mbf/comparisons/__init__.py
src/mbf/comparisons/annotator.py
src/mbf/comparisons/comparisons.py
src/mbf/comparisons/methods.py
src/mbf/comparisons/venn.py
src/mbf/externals/__init__.py
src/mbf/externals/externals.py
src/mbf/externals/prebuild.py
src/mbf/externals/snpdiffrs.py
src/mbf/externals/split_pipe.py
src/mbf/externals/util.py
src/mbf/externals/aligners/__init__.py
src/mbf/externals/aligners/base.py
src/mbf/externals/aligners/bbmap.py
src/mbf/externals/aligners/bowtie.py
src/mbf/externals/aligners/bwa.py
src/mbf/externals/aligners/salmon.py
src/mbf/externals/aligners/star.py
src/mbf/externals/aligners/subread.py
src/mbf/externals/fastq/__init__.py
src/mbf/externals/kent/__init__.py
src/mbf/externals/peak_callers/__init__.py
src/mbf/externals/peak_callers/macs2.py
src/mbf/externals/peak_callers/peakzilla.py
src/mbf/fileformats/__init__.py
src/mbf/fileformats/bed.py
src/mbf/fileformats/fasta.py
src/mbf/fileformats/gff.py
src/mbf/fileformats/prism.py
src/mbf/fileformats/util.py
src/mbf/fileformats/wiggle.py
src/mbf/functional/__init__.py
src/mbf/functional/databases.py
src/mbf/functional/great.py
src/mbf/functional/hypergeom.py
src/mbf/functional/datasets/XueEtAl2014_Macrophage_Signatures.tsv
src/mbf/functional/datasets/pwc.homo-sapiens-gene-symbol.gmt
src/mbf/functional/datasets/cpdb/CPDB_pathways_genes.tab.gz
src/mbf/functional/datasets/cpdb/info.txt
src/mbf/functional/datasets/ff/beyer_macrophage_m1_m2.txt
src/mbf/functional/datasets/ff/cebp.txt
src/mbf/functional/datasets/ff/jaktstat.txt
src/mbf/functional/datasets/ipa/Functional Annotation IPA.txt
src/mbf/functional/datasets/ipa/Functional Annotation ipa_rm.txt
