Metadata-Version: 2.1
Name: mbf
Version: 0.3
Summary: Functionality for genomics
Home-page: https://github.com/TyberiusPrime/mbf
Author: Florian Finkernagel
Author-email: finkernagel@imt.uni-marburg.de
License: mit
Platform: any
Classifier: Development Status :: 4 - Beta
Classifier: Programming Language :: Python
Requires-Python: >=3.8
Provides-Extra: testing
Provides-Extra: doc
